pomodoro_timer/__init__.py
pomodoro_timer/cli.py
pomodoro_timer/timer.py
pomodoro_timer/alarm_sounds/Gentle-wake-up-alarm-sound.mp3
tpom-1.0.0.dist-info/METADATA
tpom-1.0.0.dist-info/WHEEL
tpom-1.0.0.dist-info/entry_points.txt
tpom-1.0.0.dist-info/licenses/LICENSE
tpom-1.0.0.dist-info/RECORD
