Metadata-Version: 2.4
Name: tpom
Version: 1.0.0
Summary: A simple and elegant Pomodoro timer for the command line
Project-URL: Homepage, https://github.com/yourusername/tpom
Project-URL: Documentation, https://github.com/yourusername/tpom#readme
Project-URL: Issues, https://github.com/yourusername/tpom/issues
Project-URL: Changelog, https://github.com/yourusername/tpom/releases
Author-email: Your Name <your.email@example.com>
License-Expression: MIT
License-File: LICENSE
Keywords: cli,pomodoro,productivity,timer
Classifier: Development Status :: 4 - Beta
Classifier: Intended Audience :: End Users/Desktop
Classifier: License :: OSI Approved :: MIT License
Classifier: Operating System :: OS Independent
Classifier: Programming Language :: Python :: 3
Classifier: Programming Language :: Python :: 3.8
Classifier: Programming Language :: Python :: 3.9
Classifier: Programming Language :: Python :: 3.10
Classifier: Programming Language :: Python :: 3.11
Classifier: Programming Language :: Python :: 3.12
Classifier: Topic :: Office/Business :: Scheduling
Classifier: Topic :: Utilities
Requires-Python: >=3.8
Requires-Dist: pygame
Requires-Dist: typer>=0.9.0
Provides-Extra: dev
Requires-Dist: black; extra == 'dev'
Requires-Dist: flake8; extra == 'dev'
Requires-Dist: mypy; extra == 'dev'
Requires-Dist: pytest>=6.0; extra == 'dev'
